{
  "id": "birdkeeperbert",
  "name": "Bert",
  "class": "BIRD_KEEPER",
  "constantName": "BIRD_KEEPER_BERT",
  "versions": {
    "polished": {
      "teams": [
        {
          "matchCount": 1,
          "pokemon": [
            {
              "pokemonName": "skarmory",
              "level": 60,
              "formName": "plain",
              "moves": [
                "nightslash",
                "drillpeck",
                "airslash",
                "screech"
              ]
            },
            {
              "pokemonName": "dodrio",
              "level": 57,
              "formName": "plain",
              "moves": [
                "thrash",
                "reversal",
                "drillpeck",
                "hijumpkick"
              ]
            }
          ]
        }
      ]
    },
    "faithful": {
      "teams": [
        {
          "matchCount": 1,
          "pokemon": [
            {
              "pokemonName": "skarmory",
              "level": 60,
              "formName": "plain",
              "moves": [
                "nightslash",
                "drillpeck",
                "airslash",
                "screech"
              ]
            },
            {
              "pokemonName": "dodrio",
              "level": 57,
              "formName": "plain",
              "moves": [
                "thrash",
                "reversal",
                "drillpeck",
                "hijumpkick"
              ]
            }
          ]
        }
      ]
    }
  }
}