{
  "id": "supernerderic",
  "name": "Eric",
  "class": "SUPER_NERD",
  "constantName": "SUPER_NERD_ERIC",
  "versions": {
    "polished": {
      "teams": [
        {
          "matchCount": 1,
          "pokemon": [
            {
              "pokemonName": "grimer",
              "level": 13,
              "formName": "plain",
              "moves": [
                "disable",
                "mudslap",
                "defensecurl",
                "tackle"
              ]
            },
            {
              "pokemonName": "porygon",
              "level": 14,
              "formName": "plain",
              "moves": [
                "agility",
                "psybeam",
                "tackle",
                "conversion"
              ]
            }
          ]
        }
      ]
    },
    "faithful": {
      "teams": [
        {
          "matchCount": 1,
          "pokemon": [
            {
              "pokemonName": "grimer",
              "level": 13,
              "formName": "plain",
              "moves": [
                "disable",
                "mudslap",
                "defensecurl",
                "tackle"
              ]
            },
            {
              "pokemonName": "porygon",
              "level": 14,
              "formName": "plain",
              "moves": [
                "agility",
                "psybeam",
                "tackle",
                "conversion"
              ]
            }
          ]
        }
      ]
    }
  }
}