{
  "id": "swimmerfbarbara",
  "name": "Barbara",
  "class": "SWIMMERF",
  "constantName": "SWIMMERF_BARBARA",
  "versions": {
    "polished": {
      "teams": [
        {
          "matchCount": 1,
          "pokemon": [
            {
              "pokemonName": "starmie",
              "level": null,
              "moves": []
            }
          ]
        }
      ]
    },
    "faithful": {
      "teams": [
        {
          "matchCount": 1,
          "pokemon": [
            {
              "pokemonName": "starmie",
              "level": null,
              "moves": []
            }
          ]
        }
      ]
    }
  }
}