{
  "id": "scizor",
  "name": "Scizor",
  "dexNo": 117,
  "versions": {
    "polished": {
      "forms": {
        "plain": {
          "formNumber": 1,
          "types": [
            "bug",
            "steel"
          ],
          "abilities": [
            "swarm",
            "technician",
            "lightmetal"
          ],
          "baseStats": {
            "hp": 70,
            "attack": 130,
            "defense": 100,
            "specialAttack": 65,
            "specialDefense": 55,
            "speed": 80
          },
          "growthRate": "growthmediumfast",
          "hasGender": true,
          "movesets": {
            "levelUp": [
              {
                "name": "metalclaw",
                "level": 1
              },
              {
                "name": "bulletpunch",
                "level": 1
              },
              {
                "name": "quickattack",
                "level": 1
              },
              {
                "name": "leer",
                "level": 1
              },
              {
                "name": "focusenergy",
                "level": 5
              },
              {
                "name": "pursuit",
                "level": 9
              },
              {
                "name": "falseswipe",
                "level": 13
              },
              {
                "name": "agility",
                "level": 17
              },
              {
                "name": "wingattack",
                "level": 21
              },
              {
                "name": "bugbite",
                "level": 25
              },
              {
                "name": "slash",
                "level": 29
              },
              {
                "name": "bugbuzz",
                "level": 33
              },
              {
                "name": "defensecurl",
                "level": 37
              },
              {
                "name": "xscissor",
                "level": 41
              },
              {
                "name": "crunch",
                "level": 45
              },
              {
                "name": "closecombat",
                "level": 49
              },
              {
                "name": "ironhead",
                "level": 50
              },
              {
                "name": "swordsdance",
                "level": 57
              }
            ],
            "tm": [
              "curse",
              "toxic",
              "venoshock",
              "hiddenpower",
              "sunnyday",
              "hyperbeam",
              "lightscreen",
              "protect",
              "raindance",
              "safeguard",
              "return",
              "rocksmash",
              "doubleteam",
              "flashcannon",
              "sandstorm",
              "swift",
              "aerialace",
              "substitute",
              "facade",
              "rest",
              "attract",
              "thief",
              "steelwing",
              "roost",
              "falseswipe",
              "xscissor",
              "acrobatics",
              "gigaimpact",
              "uturn",
              "swordsdance",
              "cut",
              "fly",
              "strength",
              "agility",
              "batonpass",
              "counter",
              "doubleedge",
              "endure",
              "firepunch",
              "headbutt",
              "icepunch",
              "ironhead",
              "knockoff",
              "sleeptalk",
              "swagger",
              "thunderpunch"
            ],
            "eggMoves": [
              "batonpass",
              "bugbuzz",
              "reversal",
              "counter",
              "safeguard",
              "lightscreen",
              "nightslash"
            ]
          }
        }
      }
    },
    "faithful": {
      "forms": {
        "plain": {
          "formNumber": 1,
          "types": [
            "bug",
            "steel"
          ],
          "abilities": [
            "swarm",
            "technician",
            "lightmetal"
          ],
          "baseStats": {
            "hp": 70,
            "attack": 130,
            "defense": 100,
            "specialAttack": 65,
            "specialDefense": 55,
            "speed": 80
          },
          "growthRate": "growthmediumfast",
          "hasGender": true,
          "movesets": {
            "levelUp": [
              {
                "name": "metalclaw",
                "level": 1
              },
              {
                "name": "bulletpunch",
                "level": 1
              },
              {
                "name": "quickattack",
                "level": 1
              },
              {
                "name": "leer",
                "level": 1
              },
              {
                "name": "focusenergy",
                "level": 5
              },
              {
                "name": "pursuit",
                "level": 9
              },
              {
                "name": "falseswipe",
                "level": 13
              },
              {
                "name": "agility",
                "level": 17
              },
              {
                "name": "wingattack",
                "level": 21
              },
              {
                "name": "bugbite",
                "level": 25
              },
              {
                "name": "slash",
                "level": 29
              },
              {
                "name": "bugbuzz",
                "level": 33
              },
              {
                "name": "defensecurl",
                "level": 37
              },
              {
                "name": "xscissor",
                "level": 41
              },
              {
                "name": "crunch",
                "level": 45
              },
              {
                "name": "closecombat",
                "level": 49
              },
              {
                "name": "ironhead",
                "level": 50
              },
              {
                "name": "swordsdance",
                "level": 57
              }
            ],
            "tm": [
              "curse",
              "toxic",
              "venoshock",
              "hiddenpower",
              "sunnyday",
              "hyperbeam",
              "lightscreen",
              "protect",
              "raindance",
              "safeguard",
              "return",
              "rocksmash",
              "doubleteam",
              "flashcannon",
              "sandstorm",
              "swift",
              "aerialace",
              "substitute",
              "facade",
              "rest",
              "attract",
              "thief",
              "steelwing",
              "roost",
              "falseswipe",
              "xscissor",
              "acrobatics",
              "gigaimpact",
              "uturn",
              "swordsdance",
              "cut",
              "fly",
              "strength",
              "agility",
              "batonpass",
              "counter",
              "doubleedge",
              "endure",
              "firepunch",
              "headbutt",
              "icepunch",
              "ironhead",
              "knockoff",
              "sleeptalk",
              "swagger",
              "thunderpunch"
            ],
            "eggMoves": [
              "batonpass",
              "bugbuzz",
              "reversal",
              "counter",
              "safeguard",
              "lightscreen",
              "nightslash"
            ]
          }
        }
      }
    }
  }
}