{
  "id": "skierclarissa",
  "name": "Clarissa",
  "class": "SKIER",
  "constantName": "SKIER_CLARISSA",
  "versions": {
    "polished": {
      "teams": [
        {
          "matchCount": 1,
          "pokemon": [
            {
              "pokemonName": "piloswine",
              "level": 36,
              "formName": "plain",
              "moves": [
                {
                  "id": "takedown",
                  "type": "normal"
                },
                {
                  "id": "iciclecrash",
                  "type": "ice"
                },
                {
                  "id": "icywind",
                  "type": "ice"
                },
                {
                  "id": "magnitude",
                  "type": "ground"
                }
              ]
            }
          ]
        }
      ]
    },
    "faithful": {
      "teams": [
        {
          "matchCount": 1,
          "pokemon": [
            {
              "pokemonName": "piloswine",
              "level": 36,
              "formName": "plain",
              "moves": [
                {
                  "id": "takedown",
                  "type": "normal"
                },
                {
                  "id": "iciclecrash",
                  "type": "ice"
                },
                {
                  "id": "icywind",
                  "type": "ice"
                },
                {
                  "id": "magnitude",
                  "type": "ground"
                }
              ]
            }
          ]
        }
      ]
    }
  }
}